echarts/__init__.py
echarts/datastructure.py
echarts/option.py
echarts/plot.j2
echarts_python-0.1.2.dist-info/DESCRIPTION.rst
echarts_python-0.1.2.dist-info/METADATA
echarts_python-0.1.2.dist-info/RECORD
echarts_python-0.1.2.dist-info/WHEEL
echarts_python-0.1.2.dist-info/metadata.json
echarts_python-0.1.2.dist-info/pbr.json
echarts_python-0.1.2.dist-info/top_level.txt
